cellmapper/__init__.py
cellmapper/_docs.py
cellmapper/check.py
cellmapper/constants.py
cellmapper/logging.py
cellmapper/utils.py
cellmapper/model/_knn_backend.py
cellmapper/model/cellmapper.py
cellmapper/model/embedding.py
cellmapper/model/evaluate.py
cellmapper/model/kernel.py
cellmapper/model/mapping_operator.py
cellmapper/model/neighbors.py
cellmapper-0.2.5.dist-info/METADATA
cellmapper-0.2.5.dist-info/WHEEL
cellmapper-0.2.5.dist-info/licenses/LICENSE
cellmapper-0.2.5.dist-info/RECORD
