Metadata-Version: 2.4
Name: cellmapper
Version: 0.2.5
Summary: k-NN-based mapping of cells across representations
Project-URL: Documentation, https://cellmapper.readthedocs.io/
Project-URL: Homepage, https://github.com/quadbio/cellmapper
Project-URL: Source, https://github.com/quadbio/cellmapper
Author: Marius Lange
Maintainer-email: Marius Lange <marius.lange@bsse.ethz.ch>
License: MIT License
License-File: LICENSE
Classifier: Programming Language :: Python :: 3 :: Only
Classifier: Programming Language :: Python :: 3.11
Classifier: Programming Language :: Python :: 3.12
Classifier: Programming Language :: Python :: 3.13
Classifier: Programming Language :: Python :: 3.14
Requires-Python: >=3.11
Requires-Dist: anndata>=0.11
Requires-Dist: docrep
Requires-Dist: numpy
Requires-Dist: packaging
Requires-Dist: pandas
Requires-Dist: rich
Requires-Dist: scanpy>=1.11
Requires-Dist: scikit-learn
Requires-Dist: scipy
Requires-Dist: session-info2
Provides-Extra: dev
Requires-Dist: pre-commit; extra == 'dev'
Requires-Dist: twine>=4.0.2; extra == 'dev'
Provides-Extra: doc
Requires-Dist: docutils!=0.18.*,!=0.19.*,<0.22,>=0.8; extra == 'doc'
Requires-Dist: ipykernel; extra == 'doc'
Requires-Dist: ipython; extra == 'doc'
Requires-Dist: myst-nb>=1.1; extra == 'doc'
Requires-Dist: pandas; extra == 'doc'
Requires-Dist: setuptools; extra == 'doc'
Requires-Dist: sphinx-autodoc-typehints; extra == 'doc'
Requires-Dist: sphinx-book-theme>=1; extra == 'doc'
Requires-Dist: sphinx-copybutton; extra == 'doc'
Requires-Dist: sphinx-tabs; extra == 'doc'
Requires-Dist: sphinx>=8.1; extra == 'doc'
Requires-Dist: sphinxcontrib-bibtex>=1; extra == 'doc'
Requires-Dist: sphinxcontrib-katex; extra == 'doc'
Requires-Dist: sphinxext-opengraph; extra == 'doc'
Provides-Extra: test
Requires-Dist: coverage>=7.10; extra == 'test'
Requires-Dist: faiss-cpu; extra == 'test'
Requires-Dist: pytest; extra == 'test'
Requires-Dist: pytest-cov; extra == 'test'
Requires-Dist: squidpy>=1.6; extra == 'test'
Provides-Extra: tutorials
Requires-Dist: harmony-pytorch; extra == 'tutorials'
Requires-Dist: igraph; extra == 'tutorials'
Requires-Dist: netgraph; extra == 'tutorials'
Requires-Dist: python-louvain; extra == 'tutorials'
Requires-Dist: scvi-tools>=1.3; extra == 'tutorials'
Requires-Dist: seaborn; extra == 'tutorials'
Requires-Dist: sopa>=2; extra == 'tutorials'
Requires-Dist: squidpy>=1.6; extra == 'tutorials'
